pygalib-0.1.0.dist-info/top_level.txt
pygalib-0.1.0.dist-info/DESCRIPTION.rst
pygalib-0.1.0.dist-info/metadata.json
pygalib-0.1.0.dist-info/WHEEL
pygalib-0.1.0.dist-info/RECORD
pygalib-0.1.0.dist-info/METADATA
pygalib/ga.py
pygalib/__init__.py
