Metadata-Version: 2.0
Name: pygalib
Version: 0.1.0
Summary: A simple and easy-to-use genetic algirthm library
Home-page: https://github.com/lfzark/pygalib
Author: ark1ee
Author-email: lfzlfz@126.com
License: MIT
Keywords: genetic algorithm library
Platform: UNKNOWN
Classifier: Development Status :: 3 - Alpha
Classifier: Intended Audience :: Developers
Classifier: Topic :: Software Development :: Build Tools
Classifier: License :: OSI Approved :: MIT License
Classifier: Programming Language :: Python :: 2
Classifier: Programming Language :: Python :: 2.6
Classifier: Programming Language :: Python :: 2.7
Classifier: Programming Language :: Python :: 3
Classifier: Programming Language :: Python :: 3.2
Classifier: Programming Language :: Python :: 3.3
Classifier: Programming Language :: Python :: 3.4
